coderev/__init__.py
coderev/main.py
coderev-0.1.3.dist-info/LICENSE
coderev-0.1.3.dist-info/METADATA
coderev-0.1.3.dist-info/WHEEL
coderev-0.1.3.dist-info/entry_points.txt
coderev-0.1.3.dist-info/top_level.txt
coderev-0.1.3.dist-info/RECORD
